{
    "features": [
        {
            "geometry": {
                "coordinates": [
                    -84.1225490609997, 
                    33.8111202480005
                ], 
                "type": "Point"
            }, 
            "properties": {
                "": "<h4>SABLE ARM IN ACTS OF VALOR INC</h4>PO BOX 8706060 STONE MOUNTAIN GA 30087", 
                "marker-symbol": "museum"
            }, 
            "type": "Feature"
        }, 
        {
            "geometry": {
                "coordinates": [
                    -84.0913084719996, 
                    34.4040831480004
                ], 
                "type": "Point"
            }, 
            "properties": {
                "": "<h4>DAWSONVILLE HISTORY MUSEUM INC</h4>PO BOX 1561 DAWSONVILLE GA 30534", 
                "marker-symbol": "museum"
            }, 
            "type": "Feature"
        }, 
        {
            "geometry": {
                "coordinates": [
                    -84.2183328599996, 
                    34.2318544080005
                ], 
                "type": "Point"
            }, 
            "properties": {
                "": "<h4>DAUGHTERS OF UNION VETERANS OF THE CIVIL WAR 1861 1865</h4>4635 CONCORD VILLAGE LANE CUMMING GA 30040-1367", 
                "marker-symbol": "museum"
            }, 
            "type": "Feature"
        }, 
        {
            "geometry": {
                "coordinates": [
                    -84.5794486749996, 
                    33.8525614590005
                ], 
                "type": "Point"
            }, 
            "properties": {
                "": "<h4>TAILFIN AUTOMOTIVE MUSEUM INC</h4>4016 BRANTLEY DR AUSTELL GA 30106-1559", 
                "marker-symbol": "museum"
            }, 
            "type": "Feature"
        }, 
        {
            "geometry": {
                "coordinates": [
                    -83.8135916889997, 
                    34.2888067410005
                ], 
                "type": "Point"
            }, 
            "properties": {
                "": "<h4>INTERACTIVE NEIGHBORHOOD FOR KIDS INC</h4><b>Website:</b> <a href=\"http://www.inkfun.org\" target=\"_blank\">http://www.inkfun.org</a><br><b>Phone:</b> <a href=\"tel:7705361900\" target=\"_blank\">7705361900</a><br>999 CHESTNUT ST GAINESVILLE GA 30501-6956", 
                "marker-symbol": "museum"
            }, 
            "type": "Feature"
        }, 
        {
            "geometry": {
                "coordinates": [
                    -83.2358189389997, 
                    32.8790940580005
                ], 
                "type": "Point"
            }, 
            "properties": {
                "": "<h4>BALLS FERRY HISTORICAL PARK ASSOCIATION INC</h4>291 EH SNOW ROAD MCINTYRE GA 31054", 
                "marker-symbol": "museum"
            }, 
            "type": "Feature"
        }, 
        {
            "geometry": {
                "coordinates": [
                    -85.0295528329997, 
                    33.6109713140004
                ], 
                "type": "Point"
            }, 
            "properties": {
                "": "<h4>OKLAHOMA HISTORY AND WESTERN HERITAGE CENTER ASSOCIATION</h4>51 CAROLE TERRACE CARROLLTON GA 30116-8659", 
                "marker-symbol": "museum"
            }, 
            "type": "Feature"
        }, 
        {
            "geometry": {
                "coordinates": [
                    -84.3907879759997, 
                    33.7552434780005
                ], 
                "type": "Point"
            }, 
            "properties": {
                "": "<h4>MARINE AQUARIUM SOCIETIES OF NORTH AMERICA MASNA</h4><b>Website:</b> <a href=\"http://www.masna.org\" target=\"_blank\">http://www.masna.org</a><br>PO BOX 105603 NO 18350 ATLANTA GA 30348", 
                "marker-symbol": "museum"
            }, 
            "type": "Feature"
        }, 
        {
            "geometry": {
                "coordinates": [
                    -84.2081124299997, 
                    31.5843196660005
                ], 
                "type": "Point"
            }, 
            "properties": {
                "": "<h4>ALBANY MUSEUM OF ART INCORPORATED</h4><b>Website:</b> <a href=\"http://www.albanymuseum.com\" target=\"_blank\">http://www.albanymuseum.com</a><br><b>Phone:</b> <a href=\"tel:9124398400\" target=\"_blank\">9124398400</a><br>311 MEADOWLARK DR ALBANY GA 31707-4168", 
                "marker-symbol": "museum"
            }, 
            "type": "Feature"
        }, 
        {
            "geometry": {
                "coordinates": [
                    -84.7939983819996, 
                    32.0496441980005
                ], 
                "type": "Point"
            }, 
            "properties": {
                "": "<h4>STEWART COUNTY HISTORICAL COMMISSION INC</h4>PO BOX 818 LUMPKIN GA 31815-0818", 
                "marker-symbol": "museum"
            }, 
            "type": "Feature"
        }, 
        {
            "geometry": {
                "coordinates": [
                    -85.0294906979997, 
                    33.0387207270005
                ], 
                "type": "Point"
            }, 
            "properties": {
                "": "<h4>LAGRANGE ART MUSEUM INC</h4>112 LAFAYETTE PKWY LAGRANGE GA 30240-3209", 
                "marker-symbol": "museum"
            }, 
            "type": "Feature"
        }, 
        {
            "geometry": {
                "coordinates": [
                    -84.9758741089997, 
                    32.4661472950004
                ], 
                "type": "Point"
            }, 
            "properties": {
                "": "<h4>THE COLUMBUS MUSEUM INC</h4><b>Website:</b> <a href=\"http://www.columbusmuseum.com\" target=\"_blank\">http://www.columbusmuseum.com</a><br>1251 WYNNTON RD COLUMBUS GA 31906-2810", 
                "marker-symbol": "museum"
            }, 
            "type": "Feature"
        }, 
        {
            "geometry": {
                "coordinates": [
                    -83.3650586409997, 
                    33.8979725340005
                ], 
                "type": "Point"
            }, 
            "properties": {
                "": "<h4>UNIVERSITY OF GEORGIA</h4><b>Phone:</b> <a href=\"tel:2072384250\" target=\"_blank\">2072384250</a><br>394 S MILDGE AVE STE 100 ATHENS GA 30605", 
                "marker-symbol": "museum"
            }, 
            "type": "Feature"
        }, 
        {
            "geometry": {
                "coordinates": [
                    -84.3296957849997, 
                    33.7750465910005
                ], 
                "type": "Point"
            }, 
            "properties": {
                "": "<h4>FERNBANK INC</h4><b>Website:</b> <a href=\"http://www.fernbankmuseum.org\" target=\"_blank\">http://www.fernbankmuseum.org</a><br><b>Phone:</b> <a href=\"tel:4049296300\" target=\"_blank\">4049296300</a><br>767 CLIFTON RD NE ATLANTA GA 30307-1221", 
                "marker-symbol": "museum"
            }, 
            "type": "Feature"
        }, 
        {
            "geometry": {
                "coordinates": [
                    -84.1982298769997, 
                    33.8321813240005
                ], 
                "type": "Point"
            }, 
            "properties": {
                "": "<h4>DEKALB COUNTY BOARD OF EDUCATION</h4><b>Website:</b> <a href=\"http://www.dekalb.k12.ga.us/\" target=\"_blank\">http://www.dekalb.k12.ga.us/</a><br><b>Phone:</b> <a href=\"tel:6788747102\" target=\"_blank\">6788747102</a><br>1701 MOUNTAIN INDUSTRIAL BLVD STONE MOUNTAI GA 30083", 
                "marker-symbol": "museum"
            }, 
            "type": "Feature"
        }, 
        {
            "geometry": {
                "coordinates": [
                    -81.9608281039996, 
                    33.4751434310004
                ], 
                "type": "Point"
            }, 
            "properties": {
                "": "<h4>AUGUSTA MUSEUM OF HISTORY INC</h4><b>Website:</b> <a href=\"http://augustamuseum.org\" target=\"_blank\">http://augustamuseum.org</a><br>560 REYNOLDS ST AUGUSTA GA 30901-1430", 
                "marker-symbol": "museum"
            }, 
            "type": "Feature"
        }, 
        {
            "geometry": {
                "coordinates": [
                    -83.4500502019997, 
                    33.5321561700005
                ], 
                "type": "Point"
            }, 
            "properties": {
                "": "<h4>BRUCE WEINER MICROCAR MUSEUM INC</h4><b>Website:</b> <a href=\"http://microcarmuseum.com/index.html\" target=\"_blank\">http://microcarmuseum.com/index.html</a><br>2950 EATONTON RD MADISON GA 30650-5028", 
                "marker-symbol": "museum"
            }, 
            "type": "Feature"
        }, 
        {
            "geometry": {
                "coordinates": [
                    -85.0293987609996, 
                    33.6459874030004
                ], 
                "type": "Point"
            }, 
            "properties": {
                "": "<h4>CENTRAL OF GEORGIA RAILWAY HISTORICAL SOCIETY INC</h4>170 MUSE BRIDGE RD CARROLLTON GA 30116-5791", 
                "marker-symbol": "museum"
            }, 
            "type": "Feature"
        }, 
        {
            "geometry": {
                "coordinates": [
                    -83.7295198599996, 
                    32.4657306030005
                ], 
                "type": "Point"
            }, 
            "properties": {
                "": "<h4>UPTOWN PERRY PARTNERSHIP INC</h4>PO BOX 2030 PERRY GA 31069-6030", 
                "marker-symbol": "museum"
            }, 
            "type": "Feature"
        }, 
        {
            "geometry": {
                "coordinates": [
                    -83.6718226299997, 
                    34.6084641580005
                ], 
                "type": "Point"
            }, 
            "properties": {
                "": "<h4>GEORGIA HERITAGE ASSOCIATION INC-A DOMESTIC NONPROFIT CORPOR</h4>75 CEDAR HOLLOW RD CLEVELAND GA 30528-3692", 
                "marker-symbol": "museum"
            }, 
            "type": "Feature"
        }, 
        {
            "geometry": {
                "coordinates": [
                    -84.3735763409996, 
                    33.7339638450005
                ], 
                "type": "Point"
            }, 
            "properties": {
                "": "<h4>ZOOLOGICAL FOUNDATION OF GEORGIA INC</h4>800 CHEROKEE AVE SE ATLANTA GA 30315-1470", 
                "marker-symbol": "museum"
            }, 
            "type": "Feature"
        }, 
        {
            "geometry": {
                "coordinates": [
                    -84.9367601669996, 
                    32.5396185890004
                ], 
                "type": "Point"
            }, 
            "properties": {
                "": "<h4>THE COLUMBUS BOTANICAL GARDENS INC</h4>3603 WEEMS RD COLUMBUS GA 31909-3701", 
                "marker-symbol": "museum"
            }, 
            "type": "Feature"
        }, 
        {
            "geometry": {
                "coordinates": [
                    -83.3752063969997, 
                    33.9559110260005
                ], 
                "type": "Point"
            }, 
            "properties": {
                "": "<h4>FRIENDS OF THE GEORGIA MUSEUM OF NATURAL HISTORY INC</h4>UGA NATURAL HISTORY BLDG ATHENS GA 30602-0001", 
                "marker-symbol": "museum"
            }, 
            "type": "Feature"
        }, 
        {
            "geometry": {
                "coordinates": [
                    -84.7502997539997, 
                    33.7505139160004
                ], 
                "type": "Point"
            }, 
            "properties": {
                "": "<h4>OLD COURTHOUSE INC</h4><b>Phone:</b> <a href=\"tel:7709494090\" target=\"_blank\">7709494090</a><br>6754 BROAD ST DOUGLASVILLE GA 30134-1711", 
                "marker-symbol": "museum"
            }, 
            "type": "Feature"
        }, 
        {
            "geometry": {
                "coordinates": [
                    -82.9329447269997, 
                    34.3526272480005
                ], 
                "type": "Point"
            }, 
            "properties": {
                "": "<h4>HART REGIONAL ARTS COUNCIL IN</h4><b>Phone:</b> <a href=\"tel:7063772040\" target=\"_blank\">7063772040</a><br>338 E HOWELL ST HARTWELL GA 30643-7201", 
                "marker-symbol": "museum"
            }, 
            "type": "Feature"
        }, 
        {
            "geometry": {
                "coordinates": [
                    -83.8257081979997, 
                    34.3046268990005
                ], 
                "type": "Point"
            }, 
            "properties": {
                "": "<h4>GAINESVILLE-HALL TRUST FOR HISTORIC PRESERVATION INC</h4>380 GREEN ST NE GAINESVILLE GA 30503-2999", 
                "marker-symbol": "museum"
            }, 
            "type": "Feature"
        }, 
        {
            "geometry": {
                "coordinates": [
                    -81.1003354019996, 
                    32.0721121210005
                ], 
                "type": "Point"
            }, 
            "properties": {
                "": "<h4>RALPH MARK GILBERT CIVIL RIGHTS MUSEUM INC</h4>460 MARTIN LUTHER KING BLVD SAVANNAH GA 31401-4800", 
                "marker-symbol": "museum"
            }, 
            "type": "Feature"
        }, 
        {
            "geometry": {
                "coordinates": [
                    -84.8250868959997, 
                    33.7265512270005
                ], 
                "type": "Point"
            }, 
            "properties": {
                "": "<h4>FRIENDS OF WICKS TAVERN INC</h4>POB 2 WINSTON GA 30187-0002", 
                "marker-symbol": "museum"
            }, 
            "type": "Feature"
        }, 
        {
            "geometry": {
                "coordinates": [
                    -84.9544069239997, 
                    32.3928646850005
                ], 
                "type": "Point"
            }, 
            "properties": {
                "": "<h4>NATIONAL INFANTRY FOUNDATION INC</h4>1775 LEGACY WAY STE 220 COLUMBUS GA 31903-3675", 
                "marker-symbol": "museum"
            }, 
            "type": "Feature"
        }, 
        {
            "geometry": {
                "coordinates": [
                    -83.3972361949997, 
                    33.5270572860005
                ], 
                "type": "Point"
            }, 
            "properties": {
                "": "<h4>STEFFEN THOMAS MUSEUM & ARCHIVES INC</h4><b>Website:</b> <a href=\"http://www.steffenthomas.org\" target=\"_blank\">http://www.steffenthomas.org</a><br><b>Phone:</b> <a href=\"tel:7063427557\" target=\"_blank\">7063427557</a><br>4200 BETHANY ROAD BUCKHEAD GA 30625-1729", 
                "marker-symbol": "museum"
            }, 
            "type": "Feature"
        }, 
        {
            "geometry": {
                "coordinates": [
                    -84.6145295669996, 
                    34.0234717530005
                ], 
                "type": "Point"
            }, 
            "properties": {
                "": "<h4>KENNESAW MUSEUM FOUNDATION INC</h4><b>Website:</b> <a href=\"http://www.southernmuseum.org\" target=\"_blank\">http://www.southernmuseum.org</a><br><b>Phone:</b> <a href=\"tel:7704272117\" target=\"_blank\">7704272117</a><br>2829 CHEROKEE ST NW KENNESAW GA 30144-2823", 
                "marker-symbol": "museum"
            }, 
            "type": "Feature"
        }, 
        {
            "geometry": {
                "coordinates": [
                    -83.4868182719997, 
                    31.4486625470005
                ], 
                "type": "Point"
            }, 
            "properties": {
                "": "<h4>TIFTON TERMINAL RAILWAY MUSEUM INC</h4>120 SOUTH TIFTON AV TIFTON GA 31794", 
                "marker-symbol": "museum"
            }, 
            "type": "Feature"
        }, 
        {
            "geometry": {
                "coordinates": [
                    -83.5557078249997, 
                    34.5988910870005
                ], 
                "type": "Point"
            }, 
            "properties": {
                "": "<h4>FRIENDS OF THE FORT INC</h4>660 BETHEL TEMPLE RD DEMOREST GA 30535-3603", 
                "marker-symbol": "museum"
            }, 
            "type": "Feature"
        }, 
        {
            "geometry": {
                "coordinates": [
                    -83.2834144359996, 
                    33.9721015470005
                ], 
                "type": "Point"
            }, 
            "properties": {
                "": "<h4>GEORGIA YOUTH SCIENCE & TECHNOLOGY CENTER INC</h4>375 WINTER ST WINTERVILLE GA 30683-1408", 
                "marker-symbol": "museum"
            }, 
            "type": "Feature"
        }, 
        {
            "geometry": {
                "coordinates": [
                    -84.1535220059997, 
                    33.0469695520005
                ], 
                "type": "Point"
            }, 
            "properties": {
                "": "<h4>GEORGIA YOUTH SCIENCE & TECHNOLOGY CENTER INC</h4>419 COLLEGE DR BARNESVILLE GA 30204-1746", 
                "marker-symbol": "museum"
            }, 
            "type": "Feature"
        }, 
        {
            "geometry": {
                "coordinates": [
                    -84.3673979109997, 
                    33.8096905710005
                ], 
                "type": "Point"
            }, 
            "properties": {
                "": "<h4>NATIONAL FOUNDATION OF PATRIOTISM INC</h4><b>Website:</b> <a href=\"http://www.museumofpatriotism.org\" target=\"_blank\">http://www.museumofpatriotism.org</a><br>1927 PIEDMONT CIRCLE NE ATLANTA GA 30324-4820", 
                "marker-symbol": "museum"
            }, 
            "type": "Feature"
        }, 
        {
            "geometry": {
                "coordinates": [
                    -85.1727869349996, 
                    34.2539448300005
                ], 
                "type": "Point"
            }, 
            "properties": {
                "": "<h4>INSTITUTE FOR NORTHWEST GEORGIA HISTORY LTD</h4><b>Website:</b> <a href=\"http://www.georgiahistory.com\" target=\"_blank\">http://www.georgiahistory.com</a><br><b>Phone:</b> <a href=\"tel:7062358051\" target=\"_blank\">7062358051</a><br>305 BROAD ST ROME GA 30161-3005", 
                "marker-symbol": "museum"
            }, 
            "type": "Feature"
        }, 
        {
            "geometry": {
                "coordinates": [
                    -83.9112877109997, 
                    34.5064751610005
                ], 
                "type": "Point"
            }, 
            "properties": {
                "": "<h4>CHESTATEE WILDLIFE PRESERVE INC</h4><b>Website:</b> <a href=\"http://www.chestateewildlife.com\" target=\"_blank\">http://www.chestateewildlife.com</a><br><b>Phone:</b> <a href=\"tel:7068649411\" target=\"_blank\">7068649411</a><br>469 OLD DAHLONEGA HWY DAHLONEGA GA 30533-5745", 
                "marker-symbol": "museum"
            }, 
            "type": "Feature"
        }, 
        {
            "geometry": {
                "coordinates": [
                    -84.2090389979996, 
                    30.8766839270004
                ], 
                "type": "Point"
            }, 
            "properties": {
                "": "<h4>GRADY COUNTY HISTORICAL SOCIETY INC</h4>PO BOX 586 CAIRO GA 39828-0586", 
                "marker-symbol": "museum"
            }, 
            "type": "Feature"
        }, 
        {
            "geometry": {
                "coordinates": [
                    -84.5507483789997, 
                    33.9527581800004
                ], 
                "type": "Point"
            }, 
            "properties": {
                "": "<h4>MARIETTA MUSEUM OF HISTORY INC</h4><b>Website:</b> <a href=\"http://www.mariettahistory.org\" target=\"_blank\">http://www.mariettahistory.org</a><br>1 DEPOT STREET MARIETTA GA 30060-1900", 
                "marker-symbol": "museum"
            }, 
            "type": "Feature"
        }, 
        {
            "geometry": {
                "coordinates": [
                    -81.5489381879997, 
                    30.7204184920005
                ], 
                "type": "Point"
            }, 
            "properties": {
                "": "<h4>ST MARYS SUBMARINE MUSEUM INC</h4><b>Website:</b> <a href=\"http://www.stmaryssubmuseum.com\" target=\"_blank\">http://www.stmaryssubmuseum.com</a><br>102 W SAINT MARYS ST SAINT MARYS GA 31558-4945", 
                "marker-symbol": "museum"
            }, 
            "type": "Feature"
        }, 
        {
            "geometry": {
                "coordinates": [
                    -83.5589981159997, 
                    30.7855897550004
                ], 
                "type": "Point"
            }, 
            "properties": {
                "": "<h4>QUITMAN BROOKS COUNTY COMMUNITY CLUBS</h4><b>Phone:</b> <a href=\"tel:2292636000\" target=\"_blank\">2292636000</a><br>121 N CULPEPPER ST QUITMAN GA 31643-2048", 
                "marker-symbol": "museum"
            }, 
            "type": "Feature"
        }, 
        {
            "geometry": {
                "coordinates": [
                    -83.2267288729997, 
                    33.0813613790004
                ], 
                "type": "Point"
            }, 
            "properties": {
                "": "<h4>GEORGIAS OLD CAPITAL MUSEUM SOCIETY INC</h4>PO BOX 1177 MILLEDGEVILLE GA 31059-1177", 
                "marker-symbol": "museum"
            }, 
            "type": "Feature"
        }, 
        {
            "geometry": {
                "coordinates": [
                    -83.9935985009997, 
                    30.8387670090004
                ], 
                "type": "Point"
            }, 
            "properties": {
                "": "<h4>JACK HADLEYS BLACK HISTORY MEMORABILIA INC</h4><b>Website:</b> <a href=\"http://www.jackhadleyblackhistorymuseum.co\" target=\"_blank\">http://www.jackhadleyblackhistorymuseum.co</a><br>214 ALEXANDER ST THOMASVILLE GA 31792-4996", 
                "marker-symbol": "museum"
            }, 
            "type": "Feature"
        }, 
        {
            "geometry": {
                "coordinates": [
                    -83.7129140779996, 
                    33.7933941350005
                ], 
                "type": "Point"
            }, 
            "properties": {
                "": "<h4>MONROE ART GUILD INC</h4><b>Website:</b> <a href=\"http://monroeartguild.org\" target=\"_blank\">http://monroeartguild.org</a><br><b>Phone:</b> <a href=\"tel:7702078937\" target=\"_blank\">7702078937</a><br>205 S BROAD STREET MONROE GA 30655-0125", 
                "marker-symbol": "museum"
            }, 
            "type": "Feature"
        }, 
        {
            "geometry": {
                "coordinates": [
                    -84.1764862179996, 
                    31.5600011980005
                ], 
                "type": "Point"
            }, 
            "properties": {
                "": "<h4>ALBANY CIVIL RIGHTS INSTITUTE INC</h4><b>Website:</b> <a href=\"http://www.albancivilrights.org\" target=\"_blank\">http://www.albancivilrights.org</a><br><b>Phone:</b> <a href=\"tel:2294321698\" target=\"_blank\">2294321698</a><br>PO BOX 6036 ALBANY GA 31706-6036", 
                "marker-symbol": "museum"
            }, 
            "type": "Feature"
        }, 
        {
            "geometry": {
                "coordinates": [
                    -84.8825886959997, 
                    31.0419114460005
                ], 
                "type": "Point"
            }, 
            "properties": {
                "": "<h4>SEMINOLE ARTS COUNCIL INC</h4>PO BOX 715 DONALSONVILLE GA 39845-0715", 
                "marker-symbol": "museum"
            }, 
            "type": "Feature"
        }, 
        {
            "geometry": {
                "coordinates": [
                    -82.1210292849997, 
                    33.4352403420004
                ], 
                "type": "Point"
            }, 
            "properties": {
                "": "<h4>NATIONAL SCIENCE CENTER INC</h4>ONE 7TH STREET AUGUSTA GA 30909-9308", 
                "marker-symbol": "museum"
            }, 
            "type": "Feature"
        }, 
        {
            "geometry": {
                "coordinates": [
                    -83.5088410949996, 
                    31.4552259050005
                ], 
                "type": "Point"
            }, 
            "properties": {
                "": "<h4>TIFTON MUSEUM OF ARTS AND HERITAGE INC</h4><b>Website:</b> <a href=\"http://www.tiftonmuseum.org\" target=\"_blank\">http://www.tiftonmuseum.org</a><br><b>Phone:</b> <a href=\"tel:2293823600\" target=\"_blank\">2293823600</a><br>255 LOVE AVE TIFTON GA 31793-7362", 
                "marker-symbol": "museum"
            }, 
            "type": "Feature"
        }, 
        {
            "geometry": {
                "coordinates": [
                    -82.0341183329996, 
                    33.4656441860005
                ], 
                "type": "Point"
            }, 
            "properties": {
                "": "<h4>BOSHEARS MEMORIAL FLY-IN INC</h4>1775 HIGHLAND AVE AUGUSTA GA 30904-5302", 
                "marker-symbol": "museum"
            }, 
            "type": "Feature"
        }, 
        {
            "geometry": {
                "coordinates": [
                    -83.7336594409996, 
                    32.4574075370004
                ], 
                "type": "Point"
            }, 
            "properties": {
                "": "<h4>HOUSTON ARTS ALLIANCE</h4><b>Phone:</b> <a href=\"tel:4782185229\" target=\"_blank\">4782185229</a><br>801 MAIN ST PERRY GA 31069-3331", 
                "marker-symbol": "museum"
            }, 
            "type": "Feature"
        }, 
        {
            "geometry": {
                "coordinates": [
                    -82.0065192419997, 
                    30.8315419000004
                ], 
                "type": "Point"
            }, 
            "properties": {
                "": "<h4>OKEFENOKEE WILDLIFE LEAGUE INC</h4><b>Phone:</b> <a href=\"tel:9124967836\" target=\"_blank\">9124967836</a><br>4155 SUWANNEE CANAL RD FOLKSTON GA 31500", 
                "marker-symbol": "museum"
            }, 
            "type": "Feature"
        }, 
        {
            "geometry": {
                "coordinates": [
                    -84.3457742929996, 
                    33.6008222650005
                ], 
                "type": "Point"
            }, 
            "properties": {
                "": "<h4>WILLIAM H REYNOLDS MEMORIAL NATURE PRESERVE INC</h4><b>Website:</b> <a href=\"http://reynoldsnaturepreserve.org\" target=\"_blank\">http://reynoldsnaturepreserve.org</a><br><b>Phone:</b> <a href=\"tel:7706034188\" target=\"_blank\">7706034188</a><br>5665 REYNOLDS RD MORROW GA 30260-3731", 
                "marker-symbol": "museum"
            }, 
            "type": "Feature"
        }, 
        {
            "geometry": {
                "coordinates": [
                    -84.2320154579996, 
                    34.0207302060005
                ], 
                "type": "Point"
            }, 
            "properties": {
                "": "<h4>AUTREY MILL NATURE PRESERVE AND HERITAGE CENTER, INC</h4><b>Website:</b> <a href=\"http://www.autreymill.org\" target=\"_blank\">http://www.autreymill.org</a><br><b>Phone:</b> <a href=\"tel:6783663511\" target=\"_blank\">6783663511</a><br>9770 AUTREY MILL ROAD JOHNS CREEK GA 30022", 
                "marker-symbol": "museum"
            }, 
            "type": "Feature"
        }, 
        {
            "geometry": {
                "coordinates": [
                    -84.5823792399997, 
                    34.0313924600005
                ], 
                "type": "Point"
            }, 
            "properties": {
                "": "<h4>GEORGIA YOUTH SCIENCE AND TECHNOLOGY CENTER</h4>", 
                "marker-symbol": "museum"
            }, 
            "type": "Feature"
        }, 
        {
            "geometry": {
                "coordinates": [
                    -84.3849595759997, 
                    33.7904836370005
                ], 
                "type": "Point"
            }, 
            "properties": {
                "": "<h4>MUSEUM OF DESIGN ATLANTA INC</h4><b>Website:</b> <a href=\"http://www.museumofdesign.org\" target=\"_blank\">http://www.museumofdesign.org</a><br>GROUND FLOOR ATLANTA GA 30309-7515", 
                "marker-symbol": "museum"
            }, 
            "type": "Feature"
        }, 
        {
            "geometry": {
                "coordinates": [
                    -85.2213204859997, 
                    34.2938227160005
                ], 
                "type": "Point"
            }, 
            "properties": {
                "": "<h4>GEORGIA BOTANICAL SOCIETY INC</h4>2 IDLEWOOD CT NW ROME GA 30165-1210", 
                "marker-symbol": "museum"
            }, 
            "type": "Feature"
        }, 
        {
            "geometry": {
                "coordinates": [
                    -84.3919463449997, 
                    33.7625409070005
                ], 
                "type": "Point"
            }, 
            "properties": {
                "": "<h4>CHILDRENS MUSEUM OF ATLANTA INC</h4><b>Website:</b> <a href=\"http://www.imagineit-cma.org\" target=\"_blank\">http://www.imagineit-cma.org</a><br>275 CEN OLY PK DR NW ATLANTA GA 30313-1827", 
                "marker-symbol": "museum"
            }, 
            "type": "Feature"
        }, 
        {
            "geometry": {
                "coordinates": [
                    -84.1274067769996, 
                    33.9007620570005
                ], 
                "type": "Point"
            }, 
            "properties": {
                "": "<h4>MUSEUM FOR STUDIES IN NATURAL HISTORY</h4>PO BOX 1891 LILBURN GA 30048", 
                "marker-symbol": "museum"
            }, 
            "type": "Feature"
        }, 
        {
            "geometry": {
                "coordinates": [
                    -84.3735763409996, 
                    33.7339638450005
                ], 
                "type": "Point"
            }, 
            "properties": {
                "": "<h4>ATLANTA-FULTON COUNTY ZOO INC</h4><b>Website:</b> <a href=\"http://www.zooatlanta.org\" target=\"_blank\">http://www.zooatlanta.org</a><br>800 CHEROKEE AVE SE ATLANTA GA 30315-1470", 
                "marker-symbol": "museum"
            }, 
            "type": "Feature"
        }, 
        {
            "geometry": {
                "coordinates": [
                    -83.8321126589997, 
                    34.2461304380005
                ], 
                "type": "Point"
            }, 
            "properties": {
                "": "<h4>ELACHEE NATURE SCIENCE CENTER</h4><b>Website:</b> <a href=\"http://www.elachee.org\" target=\"_blank\">http://www.elachee.org</a><br><b>Phone:</b> <a href=\"tel:7705351976\" target=\"_blank\">7705351976</a><br>2125 ELACHEE DR GAINESVILLE GA 30504-7158", 
                "marker-symbol": "museum"
            }, 
            "type": "Feature"
        }, 
        {
            "geometry": {
                "coordinates": [
                    -83.1761043519996, 
                    34.4054664070005
                ], 
                "type": "Point"
            }, 
            "properties": {
                "": "<h4>FRANKLIN COUNTY HISTORICAL SOCIETY INC</h4>255 NORTH FORK RD LAVONIA GA 30553-4953", 
                "marker-symbol": "museum"
            }, 
            "type": "Feature"
        }, 
        {
            "geometry": {
                "coordinates": [
                    -81.0883031909997, 
                    32.0724578480005
                ], 
                "type": "Point"
            }, 
            "properties": {
                "": "<h4>KING-TISDELL COTTAGE FDN INC</h4><b>Website:</b> <a href=\"http://www.kingtisdell.org\" target=\"_blank\">http://www.kingtisdell.org</a><br>502 E HARRIS ST SAVANNAH GA 31401-4622", 
                "marker-symbol": "museum"
            }, 
            "type": "Feature"
        }, 
        {
            "geometry": {
                "coordinates": [
                    -84.3136539659997, 
                    33.8358265920004
                ], 
                "type": "Point"
            }, 
            "properties": {
                "": "<h4>GEORGIA HOSTA SOCIETY INC</h4>526 KINGS BRIDGE NE ATLANTA GA 30329-2553", 
                "marker-symbol": "museum"
            }, 
            "type": "Feature"
        }, 
        {
            "geometry": {
                "coordinates": [
                    -84.8298359859996, 
                    33.9206208920004
                ], 
                "type": "Point"
            }, 
            "properties": {
                "": "<h4>PAULDING COUNTY HISTORICAL SOCIETY INC</h4>PO BOX 333 DALLAS GA 30132-0006", 
                "marker-symbol": "museum"
            }, 
            "type": "Feature"
        }, 
        {
            "geometry": {
                "coordinates": [
                    -84.8298359859996, 
                    33.9206208920004
                ], 
                "type": "Point"
            }, 
            "properties": {
                "": "<h4>PAULDING FINE ARTS ASSOCIATION</h4><b>Phone:</b> <a href=\"tel:7704431649\" target=\"_blank\">7704431649</a><br>PO BOX 403 DALLAS GA 30132-0008", 
                "marker-symbol": "museum"
            }, 
            "type": "Feature"
        }, 
        {
            "geometry": {
                "coordinates": [
                    -84.5490844829997, 
                    33.9514228340005
                ], 
                "type": "Point"
            }, 
            "properties": {
                "": "<h4>MARIETTA-COBB MUSEUM OF ART INC</h4><b>Website:</b> <a href=\"http://mariettacobbartmuseum.org\" target=\"_blank\">http://mariettacobbartmuseum.org</a><br><b>Phone:</b> <a href=\"tel:7705281444\" target=\"_blank\">7705281444</a><br>30 ATLANTA ST SE MARIETTA GA 30060-1975", 
                "marker-symbol": "museum"
            }, 
            "type": "Feature"
        }, 
        {
            "geometry": {
                "coordinates": [
                    -83.5730900339997, 
                    34.1181197200005
                ], 
                "type": "Point"
            }, 
            "properties": {
                "": "<h4>CRAWFORD W LONG MUSEUM ASSOCIATION INC</h4>28 COLLEGE ST JEFFERSON GA 30549-1036", 
                "marker-symbol": "museum"
            }, 
            "type": "Feature"
        }, 
        {
            "geometry": {
                "coordinates": [
                    -84.7996381989997, 
                    33.3735412650005
                ], 
                "type": "Point"
            }, 
            "properties": {
                "": "<h4>COWETA COUNTY GENEALOGICAL SOCIETY INC</h4>PO BOX 1014 NEWNAN GA 30264-1014", 
                "marker-symbol": "museum"
            }, 
            "type": "Feature"
        }, 
        {
            "geometry": {
                "coordinates": [
                    -84.4820629689997, 
                    34.6970170490005
                ], 
                "type": "Point"
            }, 
            "properties": {
                "": "<h4>GILMER ARTS & HERITAGE ASSOCIATION INC</h4><b>Website:</b> <a href=\"http://www.gilmerarts.org\" target=\"_blank\">http://www.gilmerarts.org</a><br><b>Phone:</b> <a href=\"tel:7066355605\" target=\"_blank\">7066355605</a><br>207 DALTON ST ELLIJAY GA 30540-9000", 
                "marker-symbol": "museum"
            }, 
            "type": "Feature"
        }, 
        {
            "geometry": {
                "coordinates": [
                    -83.8259659439997, 
                    34.3028814300005
                ], 
                "type": "Point"
            }, 
            "properties": {
                "": "<h4>NORTHEAST GEORGIA HISTORY CENTER AT BRENAU UNIVERSITY INC</h4>PO BOX 1451 GAINESVILLE GA 30503-1451", 
                "marker-symbol": "museum"
            }, 
            "type": "Feature"
        }, 
        {
            "geometry": {
                "coordinates": [
                    -82.4138973739996, 
                    32.2162729440005
                ], 
                "type": "Point"
            }, 
            "properties": {
                "": "<h4>ALTAMA MUSEUM OF ART & HISTORY</h4>PO BOX 33 VIDALIA GA 30475", 
                "marker-symbol": "museum"
            }, 
            "type": "Feature"
        }, 
        {
            "geometry": {
                "coordinates": [
                    -81.4202668189997, 
                    31.8000714340005
                ], 
                "type": "Point"
            }, 
            "properties": {
                "": "<h4>MIDWAY MUSEUM INCORPORATED</h4>PO BOX 195 MIDWAY GA 31320-0195", 
                "marker-symbol": "museum"
            }, 
            "type": "Feature"
        }, 
        {
            "geometry": {
                "coordinates": [
                    -81.1045891429997, 
                    32.0738719480005
                ], 
                "type": "Point"
            }, 
            "properties": {
                "": "<h4>SAVANNAH COLLEGE OF ART AND DESIGN</h4><b>Website:</b> <a href=\"http://www.scad.edu/newton\" target=\"_blank\">http://www.scad.edu/newton</a><br><b>Phone:</b> <a href=\"tel:9125257191\" target=\"_blank\">9125257191</a><br>P.O. BOX 3146 SAVANNAH GA 31401-3146", 
                "marker-symbol": "museum"
            }, 
            "type": "Feature"
        }, 
        {
            "geometry": {
                "coordinates": [
                    -84.4799914359996, 
                    33.6391391470005
                ], 
                "type": "Point"
            }, 
            "properties": {
                "": "<h4>COLLEGE PARK HISTORICAL SOCIETY INC</h4>2760 LAKESHORE DRIVE COLLEGE PARK GA 30337-3033", 
                "marker-symbol": "museum"
            }, 
            "type": "Feature"
        }, 
        {
            "geometry": {
                "coordinates": [
                    -84.1463723359997, 
                    33.4455895190005
                ], 
                "type": "Point"
            }, 
            "properties": {
                "": "<h4>THE GENEALOGICAL SOCIETY OF HENRY AND CLAYTON COUNTIES INC</h4><b>Phone:</b> <a href=\"tel:7709541456\" target=\"_blank\">7709541456</a><br>72 MACON STREET MCDONOUGH GA 30253-3221", 
                "marker-symbol": "museum"
            }, 
            "type": "Feature"
        }, 
        {
            "geometry": {
                "coordinates": [
                    -84.3746662579996, 
                    33.7909702770004
                ], 
                "type": "Point"
            }, 
            "properties": {
                "": "<h4>ATLANTA BOTANICAL GARDEN INC</h4><b>Website:</b> <a href=\"http://www.atlantabotanicalgarden.org\" target=\"_blank\">http://www.atlantabotanicalgarden.org</a><br>1345 PIEDMON AVE NE ATLANTA GA 30309-3366", 
                "marker-symbol": "museum"
            }, 
            "type": "Feature"
        }, 
        {
            "geometry": {
                "coordinates": [
                    -83.9879989239997, 
                    33.9525825320005
                ], 
                "type": "Point"
            }, 
            "properties": {
                "": "<h4>LANIER MUSEUM OF NATURAL HISTORY INC</h4><b>Phone:</b> <a href=\"tel:7709324460\" target=\"_blank\">7709324460</a><br>2601 BUFORD DAM ROAD LAWRENCEVILLE GA 30246", 
                "marker-symbol": "museum"
            }, 
            "type": "Feature"
        }, 
        {
            "geometry": {
                "coordinates": [
                    -82.3830610029997, 
                    31.2349524580005
                ], 
                "type": "Point"
            }, 
            "properties": {
                "": "<h4>SOUTHERN FOREST WORLD INC</h4><b>Phone:</b> <a href=\"tel:9122854056\" target=\"_blank\">9122854056</a><br>1440 N AUGUSTA AVE WAYCROSS GA 31503-4954", 
                "marker-symbol": "museum"
            }, 
            "type": "Feature"
        }, 
        {
            "geometry": {
                "coordinates": [
                    -83.9099044679996, 
                    31.9683809250005
                ], 
                "type": "Point"
            }, 
            "properties": {
                "": "<h4>GEORGIA VETERANS MEMORIAL STATE PARK</h4><b>Website:</b> <a href=\"http://www.gastateparks.org\" target=\"_blank\">http://www.gastateparks.org</a><br><b>Phone:</b> <a href=\"tel:2292762371\" target=\"_blank\">2292762371</a><br>2459-A HIGHWAY 280 WEST CORDELE GA 31015", 
                "marker-symbol": "museum"
            }, 
            "type": "Feature"
        }, 
        {
            "geometry": {
                "coordinates": [
                    -83.2278552409996, 
                    33.0610169460004
                ], 
                "type": "Point"
            }, 
            "properties": {
                "": "<h4>LOCKERLY ARBORETUM</h4><b>Website:</b> <a href=\"http://www.lockerly.org/index.php\" target=\"_blank\">http://www.lockerly.org/index.php</a><br><b>Phone:</b> <a href=\"tel:4784522112\" target=\"_blank\">4784522112</a><br>1534 IRWINTON RD MILLEDGEVILLE GA 31061-3827", 
                "marker-symbol": "museum"
            }, 
            "type": "Feature"
        }, 
        {
            "geometry": {
                "coordinates": [
                    -84.5450773689997, 
                    33.9532214670004
                ], 
                "type": "Point"
            }, 
            "properties": {
                "": "<h4>COBB COUNTY YOUTH MUSEUM INC</h4>PO BOX 78 MARIETTA GA 30061-0078", 
                "marker-symbol": "museum"
            }, 
            "type": "Feature"
        }, 
        {
            "geometry": {
                "coordinates": [
                    -81.0943479649997, 
                    32.0787904940005
                ], 
                "type": "Point"
            }, 
            "properties": {
                "": "<h4>SAVANNAH SCIENCE MUSEUM INC</h4>PO BOX 9841 SAVANNAH GA 31412-0041", 
                "marker-symbol": "museum"
            }, 
            "type": "Feature"
        }, 
        {
            "geometry": {
                "coordinates": [
                    -81.0949003529997, 
                    32.0788311560005
                ], 
                "type": "Point"
            }, 
            "properties": {
                "": "<h4>TELFAIR MUSEUM OF ART INC</h4><b>Website:</b> <a href=\"http://www.telfair.org\" target=\"_blank\">http://www.telfair.org</a><br><b>Phone:</b> <a href=\"tel:3207715654\" target=\"_blank\">3207715654</a><br>121 BARNARD ST SAVANNAH GA 31401-3612", 
                "marker-symbol": "museum"
            }, 
            "type": "Feature"
        }, 
        {
            "geometry": {
                "coordinates": [
                    -84.8539985609997, 
                    32.8664834830005
                ], 
                "type": "Point"
            }, 
            "properties": {
                "": "<h4>IDA CASON CALLAWAY FOUNDATION</h4>PO BOX 2000 PINE MOUNTAIN GA 31822-2000", 
                "marker-symbol": "museum"
            }, 
            "type": "Feature"
        }, 
        {
            "geometry": {
                "coordinates": [
                    -84.3249249839997, 
                    33.7995046480005
                ], 
                "type": "Point"
            }, 
            "properties": {
                "": "<h4>EMORY UNIVERSITY</h4>1599 CLIFTON RD ATLANTA GA 30322", 
                "marker-symbol": "museum"
            }, 
            "type": "Feature"
        }, 
        {
            "geometry": {
                "coordinates": [
                    -84.5023632789997, 
                    33.6583625550005
                ], 
                "type": "Point"
            }, 
            "properties": {
                "": "<h4>JJS PLAYHOUSE</h4>3645 MARKETPLACE BLVD 130287 EAST POINT GA 30344-5700", 
                "marker-symbol": "museum"
            }, 
            "type": "Feature"
        }, 
        {
            "geometry": {
                "coordinates": [
                    -83.2706568779997, 
                    30.8826018240005
                ], 
                "type": "Point"
            }, 
            "properties": {
                "": "<h4>LITTLE ACTORS THEATRE OF VALDOSTA</h4>PO BOX 3601 VALDOSTA GA 31604-3601", 
                "marker-symbol": "museum"
            }, 
            "type": "Feature"
        }, 
        {
            "geometry": {
                "coordinates": [
                    -83.6668817649997, 
                    32.9339241130004
                ], 
                "type": "Point"
            }, 
            "properties": {
                "": "<h4>RICHLAND RESTORATION LEAGUE INC</h4>316 EAGLE CRST MACON GA 31211-6014", 
                "marker-symbol": "museum"
            }, 
            "type": "Feature"
        }, 
        {
            "geometry": {
                "coordinates": [
                    -83.4676376959997, 
                    33.5958925710005
                ], 
                "type": "Point"
            }, 
            "properties": {
                "": "<h4>MADISON MUSEUM OF FINE ART INC</h4>PO BOX 814 MADISON GA 30650-0814", 
                "marker-symbol": "museum"
            }, 
            "type": "Feature"
        }, 
        {
            "geometry": {
                "coordinates": [
                    -84.4345435799997, 
                    33.8035615260005
                ], 
                "type": "Point"
            }, 
            "properties": {
                "": "<h4>DECORATIVE ARTS COLLECTION INC</h4>1406 WOODMONT LN NW ATLANTA GA 30318-2867", 
                "marker-symbol": "museum"
            }, 
            "type": "Feature"
        }, 
        {
            "geometry": {
                "coordinates": [
                    -85.1262834639996, 
                    33.0544103600005
                ], 
                "type": "Point"
            }, 
            "properties": {
                "": "<h4>FACES OF FREDOM WAR MUSEUM INC</h4>1047 RIVERSIDE DRIVE LAGRANGE GA 30240-9155", 
                "marker-symbol": "museum"
            }, 
            "type": "Feature"
        }, 
        {
            "geometry": {
                "coordinates": [
                    -83.3871995089997, 
                    33.8772315250005
                ], 
                "type": "Point"
            }, 
            "properties": {
                "": "<h4>WATKINSVILLE GARDEN CLUB</h4>1170 MT LAUREL WATKINSVILLE GA 30677", 
                "marker-symbol": "museum"
            }, 
            "type": "Feature"
        }, 
        {
            "geometry": {
                "coordinates": [
                    -84.4530520409996, 
                    33.8847489730005
                ], 
                "type": "Point"
            }, 
            "properties": {
                "": "<h4>GEORGIA ARMY NATIONAL GUARD AVIATION MUSEUM INC</h4>3625 CUMBERLAND BLVD SE SUITE 660 ATLANTA GA 30339-8138", 
                "marker-symbol": "museum"
            }, 
            "type": "Feature"
        }, 
        {
            "geometry": {
                "coordinates": [
                    -82.3220466139996, 
                    32.2048217200004
                ], 
                "type": "Point"
            }, 
            "properties": {
                "": "<h4>ALTAMAHA HERITAGE CENTER INC</h4>PO BOX 1087 LYONS GA 30436-6087", 
                "marker-symbol": "museum"
            }, 
            "type": "Feature"
        }, 
        {
            "geometry": {
                "coordinates": [
                    -84.4409296089997, 
                    33.8510596280005
                ], 
                "type": "Point"
            }, 
            "properties": {
                "": "<h4>PIERCE-ARROW FOUNDATION</h4>3499 NANCY CREEK RD NW ATLANTA GA 30327-2403", 
                "marker-symbol": "museum"
            }, 
            "type": "Feature"
        }, 
        {
            "geometry": {
                "coordinates": [
                    -84.8383617899997, 
                    33.3860533280005
                ], 
                "type": "Point"
            }, 
            "properties": {
                "": "<h4>BROWNS MILL BATTLEFIELD ASSOCIATION INC</h4>76 WEST WEDGEWOOD CIRCLE NEWNAN GA 30263-1339", 
                "marker-symbol": "museum"
            }, 
            "type": "Feature"
        }, 
        {
            "geometry": {
                "coordinates": [
                    -84.4512382879997, 
                    33.4538630350004
                ], 
                "type": "Point"
            }, 
            "properties": {
                "": "<h4>PRIMATE FREEDOM PROJECT</h4>PO BOX 1623 FAYETTEVILLE GA 30214-6503", 
                "marker-symbol": "museum"
            }, 
            "type": "Feature"
        }, 
        {
            "geometry": {
                "coordinates": [
                    -84.4504972699997, 
                    33.4627568760005
                ], 
                "type": "Point"
            }, 
            "properties": {
                "": "<h4>PROPHET EVERETTS BLACK HISTORY MUSEUM AND CULTURAL CENTER OF</h4>740 GYLNN ST N FAYETTEVILLE GA 30215", 
                "marker-symbol": "museum"
            }, 
            "type": "Feature"
        }, 
        {
            "geometry": {
                "coordinates": [
                    -81.9700431369997, 
                    33.4767607420005
                ], 
                "type": "Point"
            }, 
            "properties": {
                "": "<h4>BROAD STREET ARTISTS ROW</h4>1006 BROAD STREET AUGUSTA GA 30901-1120", 
                "marker-symbol": "museum"
            }, 
            "type": "Feature"
        }, 
        {
            "geometry": {
                "coordinates": [
                    -84.3656373369997, 
                    33.9611206880004
                ], 
                "type": "Point"
            }, 
            "properties": {
                "": "<h4>NORTH FULTON MASTER GARDENERS INC</h4>PO BOX 566651 ATLANTA GA 31156-6651", 
                "marker-symbol": "museum"
            }, 
            "type": "Feature"
        }, 
        {
            "geometry": {
                "coordinates": [
                    -84.3021372849997, 
                    33.7862082550005
                ], 
                "type": "Point"
            }, 
            "properties": {
                "": "<h4>WOODLANDS GARDEN OF DECATUR INC</h4>932 SCOTT BLVD DECATUR GA 30030-1302", 
                "marker-symbol": "museum"
            }, 
            "type": "Feature"
        }, 
        {
            "geometry": {
                "coordinates": [
                    -84.3940104079996, 
                    33.7623082660004
                ], 
                "type": "Point"
            }, 
            "properties": {
                "": "<h4>GEORGIA AQUARIUM FOUNDATION INC</h4><b>Website:</b> <a href=\"http://www.georgiaaquarium.org\" target=\"_blank\">http://www.georgiaaquarium.org</a><br><b>Phone:</b> <a href=\"tel:4045814000\" target=\"_blank\">4045814000</a><br>225 BAKER ST NW ATLANTA GA 30313-1809", 
                "marker-symbol": "museum"
            }, 
            "type": "Feature"
        }, 
        {
            "geometry": {
                "coordinates": [
                    -84.4165035299997, 
                    33.7685903740004
                ], 
                "type": "Point"
            }, 
            "properties": {
                "": "<h4>HISTORIC WESTSIDE CULTURAL ARTS COUNCIL</h4><b>Website:</b> <a href=\"http://www.hwcac.com\" target=\"_blank\">http://www.hwcac.com</a><br>510 LINDSAY ST NW ATLANTA GA 30316", 
                "marker-symbol": "museum"
            }, 
            "type": "Feature"
        }, 
        {
            "geometry": {
                "coordinates": [
                    -84.8583972629997, 
                    34.5109569670005
                ], 
                "type": "Point"
            }, 
            "properties": {
                "": "<h4>BLACKSTOCK SOUTHERN HERITAGE AGRICULTURAL MUSEUM INC</h4>260 LANCE RD NE CALHOUN GA 30701-4927", 
                "marker-symbol": "museum"
            }, 
            "type": "Feature"
        }, 
        {
            "geometry": {
                "coordinates": [
                    -84.3420193299997, 
                    33.7648934930004
                ], 
                "type": "Point"
            }, 
            "properties": {
                "": "<h4>DASHBOARD CO-OP</h4>1390 MCLENDON AVE NE ATLANTA GA 30307-2030", 
                "marker-symbol": "museum"
            }, 
            "type": "Feature"
        }, 
        {
            "geometry": {
                "coordinates": [
                    -84.3708090089997, 
                    33.8490034930005
                ], 
                "type": "Point"
            }, 
            "properties": {
                "": "<h4>HISTORIC WESTSIDE GARDENS</h4><b>Website:</b> <a href=\"http://www.historicwestsidegardens.org\" target=\"_blank\">http://www.historicwestsidegardens.org</a><br>3338 PEACHTREE RD NE APT 1108 ATLANTA GA 30326-3032", 
                "marker-symbol": "museum"
            }, 
            "type": "Feature"
        }, 
        {
            "geometry": {
                "coordinates": [
                    -84.3077735489996, 
                    33.9320839010005
                ], 
                "type": "Point"
            }, 
            "properties": {
                "": "<h4>GEORGIA CHAPTER OF THE AMERICAN CHESTNUT FOUNDATION</h4>1952 HUNTINGTON HALL CT DUNWOODY GA 30338-5713", 
                "marker-symbol": "museum"
            }, 
            "type": "Feature"
        }, 
        {
            "geometry": {
                "coordinates": [
                    -84.1388888869997, 
                    34.2157423470005
                ], 
                "type": "Point"
            }, 
            "properties": {
                "": "<h4>COL HIRAM PARKS BELL SOUTHERN HIST & GENEALOGICAL RESEARCH C</h4>PO BOX 2299 CUMMING GA 30028-6501", 
                "marker-symbol": "museum"
            }, 
            "type": "Feature"
        }, 
        {
            "geometry": {
                "coordinates": [
                    -84.2568332779996, 
                    33.8374708970005
                ], 
                "type": "Point"
            }, 
            "properties": {
                "": "<h4>CARTOONING FOR PEACE - AMERICA INC</h4>1860 MONTREAL ROAD TUCKER GA 30084-5709", 
                "marker-symbol": "museum"
            }, 
            "type": "Feature"
        }, 
        {
            "geometry": {
                "coordinates": [
                    -84.2991561549997, 
                    34.0732500850004
                ], 
                "type": "Point"
            }, 
            "properties": {
                "": "<h4>ALPHARETTA ARBORETUM INCORPORATED</h4><b>Website:</b> <a href=\"http://alpharetta-arboretum.org\" target=\"_blank\">http://alpharetta-arboretum.org</a><br>PO BOX 1305 ALPHARETTA GA 30009", 
                "marker-symbol": "museum"
            }, 
            "type": "Feature"
        }, 
        {
            "geometry": {
                "coordinates": [
                    -85.2677315749997, 
                    34.8830546280005
                ], 
                "type": "Point"
            }, 
            "properties": {
                "": "<h4>VETERANS OF ALL WARS MUSEUM INC</h4>71 RED BELT RD CHICKAMAUGA GA 30707-3316", 
                "marker-symbol": "museum"
            }, 
            "type": "Feature"
        }, 
        {
            "geometry": {
                "coordinates": [
                    -83.0394971319997, 
                    34.4815871630005
                ], 
                "type": "Point"
            }, 
            "properties": {
                "": "<h4>HART COUNTY BOTANICAL GARDEN INC</h4>1700 HARBOR LIGHT MARINA ROAD LAVONIA GA 30553-3212", 
                "marker-symbol": "museum"
            }, 
            "type": "Feature"
        }, 
        {
            "geometry": {
                "coordinates": [
                    -84.5905359339997, 
                    33.4293577100005
                ], 
                "type": "Point"
            }, 
            "properties": {
                "": "<h4>LINDAS ATTIC INC</h4>101 LANTERN VW PEACHTREE CTY GA 30214-4724", 
                "marker-symbol": "museum"
            }, 
            "type": "Feature"
        }, 
        {
            "geometry": {
                "coordinates": [
                    -84.2093865989997, 
                    33.9421808090005
                ], 
                "type": "Point"
            }, 
            "properties": {
                "": "<h4>NORCROSS HISTORY CENTER INC</h4>PO BOX 1523 NORCROSS GA 30091-1523", 
                "marker-symbol": "museum"
            }, 
            "type": "Feature"
        }, 
        {
            "geometry": {
                "coordinates": [
                    -84.5823792399997, 
                    34.0313924600005
                ], 
                "type": "Point"
            }, 
            "properties": {
                "": "<h4>KENNESAW STATE UNIVERSITY FOUNDATION</h4>", 
                "marker-symbol": "museum"
            }, 
            "type": "Feature"
        }, 
        {
            "geometry": {
                "coordinates": [
                    -84.4676276479997, 
                    33.9044922320005
                ], 
                "type": "Point"
            }, 
            "properties": {
                "": "<h4>KYEREMA FOUNDATION</h4>PO BOX 673381 MARIETTA GA 30006-0057", 
                "marker-symbol": "museum"
            }, 
            "type": "Feature"
        }, 
        {
            "geometry": {
                "coordinates": [
                    -84.6308082269996, 
                    34.0104397000005
                ], 
                "type": "Point"
            }, 
            "properties": {
                "": "<h4>SMITH GILBERT ARBORETUM FOUNDATION INC</h4><b>Website:</b> <a href=\"http://www.smithgilbertgardens.com\" target=\"_blank\">http://www.smithgilbertgardens.com</a><br><b>Phone:</b> <a href=\"tel:7709190248\" target=\"_blank\">7709190248</a><br>2382 PINE MOUNTAIN ROAD KENNESAW GA 30152", 
                "marker-symbol": "museum"
            }, 
            "type": "Feature"
        }, 
        {
            "geometry": {
                "coordinates": [
                    -84.3941928079997, 
                    33.6062552000005
                ], 
                "type": "Point"
            }, 
            "properties": {
                "": "<h4>NATIONAL MUSEUM OF COMMERCIALAVIATION INCORPORATED</h4><b>Website:</b> <a href=\"http://www.nationalaviationmuseum.com\" target=\"_blank\">http://www.nationalaviationmuseum.com</a><br><b>Phone:</b> <a href=\"tel:4046759266\" target=\"_blank\">4046759266</a><br>5442 FRONTAGE RD STE 110 FOREST PARK GA 30297-2543", 
                "marker-symbol": "museum"
            }, 
            "type": "Feature"
        }, 
        {
            "geometry": {
                "coordinates": [
                    -85.0638498419997, 
                    33.0244635210005
                ], 
                "type": "Point"
            }, 
            "properties": {
                "": "<h4>EXPLORATION IN ANTIQUITY INC</h4>130 GORDON COMRCL DR LAGRANGE GA 30240-5740", 
                "marker-symbol": "museum"
            }, 
            "type": "Feature"
        }, 
        {
            "geometry": {
                "coordinates": [
                    -83.3747084389997, 
                    33.9496911640005
                ], 
                "type": "Point"
            }, 
            "properties": {
                "": "<h4>ARCH FOUNDATION FOR UNIVERSITY OF GEORGIA</h4>", 
                "marker-symbol": "museum"
            }, 
            "type": "Feature"
        }, 
        {
            "geometry": {
                "coordinates": [
                    -82.1356285029997, 
                    33.5425011450005
                ], 
                "type": "Point"
            }, 
            "properties": {
                "": "<h4>ARTISTS GUILD OF COLUMBIA COUNTY</h4>PO BOX 2205 EVANS GA 30809-2205", 
                "marker-symbol": "museum"
            }, 
            "type": "Feature"
        }, 
        {
            "geometry": {
                "coordinates": [
                    -84.2780673719997, 
                    33.2256203160005
                ], 
                "type": "Point"
            }, 
            "properties": {
                "": "<h4>CANDLER FIELD MUSEUM INC</h4>129 SKY HARBOR WAY GRIFFIN GA 30224-4873", 
                "marker-symbol": "museum"
            }, 
            "type": "Feature"
        }, 
        {
            "geometry": {
                "coordinates": [
                    -83.8259659439997, 
                    34.3028814300005
                ], 
                "type": "Point"
            }, 
            "properties": {
                "": "<h4>GAINESVILLE-HALL COUNTY BLACK HISTORY SOCIETY INC</h4>PO BOX 423 GAINESVILLE GA 30503-0423", 
                "marker-symbol": "museum"
            }, 
            "type": "Feature"
        }, 
        {
            "geometry": {
                "coordinates": [
                    -84.5450773689997, 
                    33.9532214670004
                ], 
                "type": "Point"
            }, 
            "properties": {
                "": "<h4>FRIENDS OF THE STRAND INC</h4>PO BOX 4186 MARIETTA GA 30061-4186", 
                "marker-symbol": "museum"
            }, 
            "type": "Feature"
        }, 
        {
            "geometry": {
                "coordinates": [
                    -83.0752880559996, 
                    31.0409903050004
                ], 
                "type": "Point"
            }, 
            "properties": {
                "": "<h4>LANIER COUNTY HISTORICAL SOCIETY INC</h4>49 WEST MAIN STREET LAKELAND GA 31635-6834", 
                "marker-symbol": "museum"
            }, 
            "type": "Feature"
        }, 
        {
            "geometry": {
                "coordinates": [
                    -84.5422522939996, 
                    33.9502432690005
                ], 
                "type": "Point"
            }, 
            "properties": {
                "": "<h4>MARIETTA AERONAUTICAL MUSEUM AND EDUCATION CENTER INC</h4>358 ROSWELL ST SE STE 1110 MARIETTA GA 30060-8200", 
                "marker-symbol": "museum"
            }, 
            "type": "Feature"
        }, 
        {
            "geometry": {
                "coordinates": [
                    -83.2094373999997, 
                    33.4193162860005
                ], 
                "type": "Point"
            }, 
            "properties": {
                "": "<h4>PLANTATION REFLECTION GARDEN INC</h4><b>Phone:</b> <a href=\"tel:7064670893\" target=\"_blank\">7064670893</a><br>1090 HENRYS HILL GREENSBORO GA 30642-5209", 
                "marker-symbol": "museum"
            }, 
            "type": "Feature"
        }, 
        {
            "geometry": {
                "coordinates": [
                    -84.8195379689997, 
                    33.4786350700005
                ], 
                "type": "Point"
            }, 
            "properties": {
                "": "<h4>DUNAWAY GARDENS FOUNDATION INC</h4><b>Website:</b> <a href=\"http://www.dunawaygardens.com\" target=\"_blank\">http://www.dunawaygardens.com</a><br>3218 ROSCOE RD NEWNAN GA 30263-4056", 
                "marker-symbol": "museum"
            }, 
            "type": "Feature"
        }, 
        {
            "geometry": {
                "coordinates": [
                    -84.4766632449997, 
                    33.6406303190005
                ], 
                "type": "Point"
            }, 
            "properties": {
                "": "<h4>WORLD BOTANICAL GARDENS CONSERVATIO N FUND</h4>4215 FREDERICKSBURG DR COLLEGE PARK GA 30337", 
                "marker-symbol": "museum"
            }, 
            "type": "Feature"
        }, 
        {
            "geometry": {
                "coordinates": [
                    -84.3807888449996, 
                    33.8651872650005
                ], 
                "type": "Point"
            }, 
            "properties": {
                "": "<h4>BLUE HERON NATURE PRESERVE INC</h4><b>Phone:</b> <a href=\"tel:4048148228\" target=\"_blank\">4048148228</a><br>4055 ROSWELL RD NE ATLANTA GA 30342-4145", 
                "marker-symbol": "museum"
            }, 
            "type": "Feature"
        }, 
        {
            "geometry": {
                "coordinates": [
                    -84.0946758509996, 
                    31.5675636230005
                ], 
                "type": "Point"
            }, 
            "properties": {
                "": "<h4>CHEHAW WILD ANIMAL PARK</h4>", 
                "marker-symbol": "museum"
            }, 
            "type": "Feature"
        }, 
        {
            "geometry": {
                "coordinates": [
                    -84.5574293169997, 
                    33.4269344080005
                ], 
                "type": "Point"
            }, 
            "properties": {
                "": "<h4>LINDA'S PLAYHOUSE</h4><b>Phone:</b> <a href=\"tel:7704871979\" target=\"_blank\">7704871979</a><br>1991 HIGHWAY 54 W FAYETTEVILLE GA 30214", 
                "marker-symbol": "museum"
            }, 
            "type": "Feature"
        }, 
        {
            "geometry": {
                "coordinates": [
                    -83.8265174879996, 
                    34.3013004780005
                ], 
                "type": "Point"
            }, 
            "properties": {
                "": "<h4>INK INTERACTIVE NEIGHBORHOOD FOR KIDS</h4><b>Website:</b> <a href=\"http://www.inkfun.org\" target=\"_blank\">http://www.inkfun.org</a><br><b>Phone:</b> <a href=\"tel:7705039177\" target=\"_blank\">7705039177</a><br>203 GREEN ST NE GAINESVILLE GA 30501", 
                "marker-symbol": "museum"
            }, 
            "type": "Feature"
        }, 
        {
            "geometry": {
                "coordinates": [
                    -84.8964280639997, 
                    32.4873911970005
                ], 
                "type": "Point"
            }, 
            "properties": {
                "": "<h4>PATTERSON PLANETARIUM</h4><b>Phone:</b> <a href=\"tel:7065693622\" target=\"_blank\">7065693622</a><br>2900 WOODRUFF FARM RD COLUMBUS GA 31907", 
                "marker-symbol": "museum"
            }, 
            "type": "Feature"
        }, 
        {
            "geometry": {
                "coordinates": [
                    -84.3930568509996, 
                    33.8032081070004
                ], 
                "type": "Point"
            }, 
            "properties": {
                "": "<h4>SOUTHERN ARTS FEDERATION</h4><b>Phone:</b> <a href=\"tel:4048747244\" target=\"_blank\">4048747244</a><br>1800 PEACHTREE ST NW ATLANTA GA 30309", 
                "marker-symbol": "museum"
            }, 
            "type": "Feature"
        }
    ], 
    "type": "FeatureCollection"
}